LICENCE.txt
MANIFEST.in
README.rst
setup.py
yahoo/__init__.py
yahoo.egg-info/PKG-INFO
yahoo.egg-info/SOURCES.txt
yahoo.egg-info/dependency_links.txt
yahoo.egg-info/requires.txt
yahoo.egg-info/top_level.txt
yahoo/examples/__init__.py
yahoo/examples/example.py